<?xml version='1.0' encoding='UTF-8'?>
<song xmlns="http://openlyrics.info/namespace/2009/song" version="0.8" createdIn="OpenLP 3.1.7" modifiedIn="OpenLP 3.1.7" modifiedDate="2025-10-05T14:02:07">
  <properties>
    <titles>
      <title>Bądźże pozdrowiona Hostyjo żywa</title>
    </titles>
    <authors>
      <author>a</author>
    </authors>
  </properties>
  <lyrics>
    <verse name="v1">
      <lines>1. Bądźże pozdrowiona Hostyjo żywa!<br/>W której Jezus Chrystus Bóstwo ukrywa.</lines>
    </verse>
    <verse name="c1">
      <lines>Witaj Jezu, Synu Maryi.<br/>Tyś jest Bóg prawdziwy w świętej Hostyi.</lines>
    </verse>
    <verse name="v2">
      <lines>2. Bądźże pozdrowione, drzewo żywota!<br/>Niech kwitnie niewinność, anielska cnota.</lines>
    </verse>
    <verse name="c2">
      <lines>Witaj Jezu, Synu Maryi.<br/>Tyś jest Bóg prawdziwy w świętej Hostyi.</lines>
    </verse>
    <verse name="v3">
      <lines>3. Bądźże pozdrowiony, Baranku Boży !<br/>Zbaw nas, gdy miecz Pański na złych się sroży!</lines>
    </verse>
    <verse name="c3">
      <lines>Witaj Jezu, Synu Maryi.<br/>Tyś jest Bóg prawdziwy w świętej Hostyi.</lines>
    </verse>
    <verse name="v4">
      <lines>4. Bądźże pozdrowiony, Anielski Chlebie!<br/>W tym tu sakramencie wielbimy Ciebie!</lines>
    </verse>
    <verse name="c4">
      <lines>Witaj Jezu, Synu Maryi.<br/>Tyś jest Bóg prawdziwy w świętej Hostyi.</lines>
    </verse>
    <verse name="v5">
      <lines>5. Bądźże pozdrowiona, święta Krynico!<br/>Serce Przenajświętsze, łąski świątnico!</lines>
    </verse>
    <verse name="c5">
      <lines>Witaj Jezu, Synu Maryi.<br/>Tyś jest Bóg prawdziwy w świętej Hostyi.</lines>
    </verse>
    <verse name="v6">
      <lines>6. Bądźże pozdrowiony, Boski Kapłanie!<br/>Przyjm nasze ofiary, usłysz błaganie.</lines>
    </verse>
    <verse name="c6">
      <lines>Witaj Jezu, Synu Maryi.<br/>Tyś jest Bóg prawdziwy w świętej Hostyi.</lines>
    </verse>
    <verse name="v7">
      <lines>7. Bądźże pozdrowiona, Żywa Ofiaro!<br/>Broń nas przed doczesną i wieczną karą!</lines>
    </verse>
    <verse name="c7">
      <lines>Witaj Jezu, Synu Maryi.<br/>Tyś jest Bóg prawdziwy w świętej Hostyi.</lines>
    </verse>
    <verse name="v8">
      <lines>8. Bądźże pozdrowiony, dobry Pasterzu!<br/>Tyś dał duszę swoją za nas na krzyżu!</lines>
    </verse>
    <verse name="c8">
      <lines>Witaj Jezu, Synu Maryi.<br/>Tyś jest Bóg prawdziwy w świętej Hostyi.</lines>
    </verse>
    <verse name="v9">
      <lines>9. Bądźże pozdrowiony, wszechmocny Boże!<br/>Już Cię kocham szczerze, jak serce może!</lines>
    </verse>
    <verse name="c9">
      <lines>Witaj Jezu, Synu Maryi.<br/>Tyś jest Bóg prawdziwy w świętej Hostyi.</lines>
    </verse>
  </lyrics>
</song>
