<?xml version='1.0' encoding='UTF-8'?>
<song xmlns="http://openlyrics.info/namespace/2009/song" version="0.8" createdIn="OpenLP 3.1.7" modifiedIn="OpenLP 3.1.7" modifiedDate="2021-01-16T18:02:48">
  <properties>
    <titles>
      <title>Przykazanie nowe daję wam</title>
      <title>gdybym mówił językami ludzi i aniołów</title>
    </titles>
    <authors>
      <author>a</author>
    </authors>
  </properties>
  <lyrics>
    <verse name="c1">
      <lines>Przykazanie nowe daję wam <br/>Byście się wzajemnie miłowali.</lines>
    </verse>
    <verse name="v1">
      <lines>Gdybym mówił językami ludzi i aniołów <br/>a miłości bym nie miał <br/>Stałbym się jak miedź brzęcząca <br/>albo cymbał brzmiący.</lines>
    </verse>
    <verse name="c2">
      <lines>Przykazanie nowe daję wam <br/>Byście się wzajemnie miłowali.</lines>
    </verse>
    <verse name="v2">
      <lines>Gdybym posiadał wszystką wiedzę <br/>i wiarę taką, iżbym góry przenosił,<br/>Lecz miłości bym nie miał <br/>byłbym niczym.</lines>
    </verse>
    <verse name="c3">
      <lines>Przykazanie nowe daję wam <br/>Byście się wzajemnie miłowali.</lines>
    </verse>
    <verse name="v3">
      <lines>I gdybym rozdał ubogim całą swoją majętność <br/>a ciało swe wystawił na spalenie,<br/>Lecz miłości bym nie miał <br/>nic mi nie pomoże.</lines>
    </verse>
    <verse name="c4">
      <lines>Przykazanie nowe daję wam <br/>Byście się wzajemnie miłowali.</lines>
    </verse>
    <verse name="v4">
      <lines>Miłość jest cierpliwa <br/>Miłość jest łaskawa,<br/>Miłość nie zazdrości <br/>Nie szuka poklasku.</lines>
    </verse>
    <verse name="c5">
      <lines>Przykazanie nowe daję wam <br/>Byście się wzajemnie miłowali.</lines>
    </verse>
    <verse name="v5">
      <lines>Miłość nie unosi się pychą <br/>ale jest pokorna.<br/>Miłość nie szuka swego  <br/>gniewem się nie unosi.</lines>
    </verse>
    <verse name="c6">
      <lines>Przykazanie nowe daję wam <br/>Byście się wzajemnie miłowali.</lines>
    </verse>
    <verse name="v6">
      <lines>Miłość nie pamięta złego <br/>nie cieszy się z niesprawiedliwości,<br/>Lecz współweseli się z prawdą <br/>miłość wszystko zniesie i przetrzyma.</lines>
    </verse>
    <verse name="c7">
      <lines>Przykazanie nowe daję wam <br/>Byście się wzajemnie miłowali.</lines>
    </verse>
    <verse name="v7">
      <lines>Miłość nigdy nie ustaje <br/>zniknie to, co jest cząstkowe.<br/>Teraz trwa wiara, nadzieja i miłość <br/>z nich zaś największa jest miłość.</lines>
    </verse>
  </lyrics>
</song>
